mcp_index/__init__.py
mcp_index/utils.py
mcp_marketplace/__init__.py
mcp_marketplace/utils.py
mcp_index-0.0.1.dist-info/METADATA
mcp_index-0.0.1.dist-info/WHEEL
mcp_index-0.0.1.dist-info/top_level.txt
mcp_index-0.0.1.dist-info/RECORD
