Metadata-Version: 2.4
Name: mcp_index
Version: 0.0.1
Summary: Open Source MCP Index | Marketplace Python Registry Service and Html Plugin to Integrate with your AI Application
Author: AI Agent Hub
Author-email: AI Agent Hub <dingo0927@126.com>
Maintainer-email: AI Agent Hub <dingo0927@126.com>
Project-URL: HomePage, http://www.deepnlp.org/store/ai-agent/mcp-server
Project-URL: Documentation, https://github.com/AI-Agent-Hub/mcp-marketplace
Project-URL: Repository, https://github.com/AI-Agent-Hub/mcp-marketplace
Keywords: MCP Marketplace,AI Agent Marketplace,AI Agent Directory
Classifier: Development Status :: 4 - Beta
Classifier: Programming Language :: Python
Requires-Python: >=3.4
Requires-Dist: requests>=2.17.0
Dynamic: author
Dynamic: requires-python
